{"type": "Feature", "id": 12513879, "geometry": {"type": "Point", "coordinates": [44.270802, 32.970798]}, "properties": {"woe:id": 12513879, "woe:parent_id": 1979404, "woe:name": "Al Iskandariyah New Airport", "woe:placetype": 14, "woe:placetype_name": "Airport", "woe:lang": "ENG", "iso:country": "IQ", "meta:provider": ["geoplanet:7.3.1", "geoplanet:7.3.2", "geoplanet:7.4.0", "geoplanet:7.4.1", "geoplanet:7.5.1", "geoplanet:7.5.2", "geoplanet:7.6.0", "geoplanet:7.8.1", "geoplanet:7.9.0", "geoplanet:7.10.0", "geoplanet:8.0.0", "woeplanet:8.0.0"], "meta:indexed": "2020-08-20T20:56:20.432304", "meta:updated": "2020-10-14T11:46:05.853900", "woe:hierarchy": {"continent": 24865671, "country": 23424855, "town": 0, "planet": 1, "county": 55999979, "suburb": 0, "state": 2345839, "region": 0, "localadmin": 0}, "woe:timezone_id": 28350811, "woe:hash": "svz7x6jhb6nx", "woe:centroid": [44.270802, 32.970798], "geom:latitude": 32.970798, "geom:longitude": 44.270802, "geom:hash": "svz7x6jhb6nx", "woe:latitude": 32.970798, "geom:centroid": [44.270802, 32.970798], "woe:longitude": 44.270802, "woe:repo": "woeplanet-airport-iq", "geom:area": 0.0, "woe:scale": 19}}