{"type": "Feature", "id": 12513918, "properties": {"woe:id": 12513918, "woe:parent_id": 1977286, "woe:name": "Qayyarah West Airport", "woe:placetype": 14, "woe:placetype_name": "Airport", "woe:lang": "ENG", "iso:country": "IQ", "meta:provider": ["geoplanet:7.3.1", "geoplanet:7.3.2", "geoplanet:7.4.0", "geoplanet:7.4.1", "geoplanet:7.5.1", "geoplanet:7.5.2", "geoplanet:7.6.0", "geoplanet:7.8.1", "geoplanet:7.9.0", "geoplanet:7.10.0", "geoplanet:8.0.0", "woeplanet:8.0.0"], "meta:indexed": "2020-08-20T20:56:20.465515", "meta:updated": "2020-08-22T02:50:50.730816", "woe:hierarchy": {"continent": 24865671, "country": 23424855, "town": 0, "planet": 1, "county": 55999964, "suburb": 0, "state": 2345847, "region": 0, "localadmin": 0}, "woe:timezone_id": 28350811, "woe:hash": "syqemr6kq361", "woe:centroid": [43.124699, 35.768101], "geom:latitude": 35.768101, "geom:longitude": 43.124699, "geom:hash": "syqemr6kq361", "woe:latitude": 35.768101, "geom:centroid": [43.124699, 35.768101], "woe:longitude": 43.124699, "woe:repo": "woeplanet-airport-iq"}, "geometry": {"coordinates": [43.124699, 35.768101], "type": "Point"}}