{"type": "Feature", "id": 12513904, "geometry": {"type": "Point", "coordinates": [41.4417, 33.8111]}, "properties": {"woe:id": 12513904, "woe:parent_id": 1971112, "woe:name": "H1 New Airport", "woe:placetype": 14, "woe:placetype_name": "Airport", "woe:lang": "ENG", "iso:country": "IQ", "meta:provider": ["geoplanet:7.3.1", "geoplanet:7.3.2", "geoplanet:7.4.0", "geoplanet:7.4.1", "geoplanet:7.5.1", "geoplanet:7.5.2", "geoplanet:7.6.0", "geoplanet:7.8.1", "geoplanet:7.9.0", "geoplanet:7.10.0", "geoplanet:8.0.0", "woeplanet:8.0.0"], "meta:indexed": "2020-08-20T20:56:20.453393", "meta:updated": "2020-10-14T11:46:05.857075", "woe:hierarchy": {"continent": 24865671, "country": 23424855, "town": 0, "planet": 1, "county": 55999893, "suburb": 0, "state": 2345833, "region": 0, "localadmin": 0}, "woe:timezone_id": 28350811, "woe:hash": "syj2r50gvtg5", "woe:centroid": [41.4417, 33.8111], "geom:latitude": 33.8111, "geom:longitude": 41.4417, "geom:hash": "syj2r50gvtg5", "woe:latitude": 33.8111, "geom:centroid": [41.4417, 33.8111], "woe:longitude": 41.4417, "woe:repo": "woeplanet-airport-iq", "geom:area": 0.0, "woe:scale": 19}}